openapi_bundle.py
openapi_bundle-0.2.dist-info/METADATA
openapi_bundle-0.2.dist-info/RECORD
openapi_bundle-0.2.dist-info/WHEEL
openapi_bundle-0.2.dist-info/entry_points.txt
openapi_bundle-0.2.dist-info/top_level.txt
