Metadata-Version: 2.1
Name: openapi-bundle
Version: 0.2
Summary: Combine multiple json or yaml files into a single readable OpenAPI specification.
Home-page: https://github.com/windtail/openapi-bundle
Author: UNKNOWN
Author-email: UNKNOWN
License: UNKNOWN
Platform: UNKNOWN
Requires-Dist: Click
Requires-Dist: oyaml
